llmvault/__init__.py
llmvault/attacks/__init__.py
llmvault/attacks/base.py
llmvault/attacks/engine.py
llmvault/attacks/loader.py
llmvault/attacks/templates.py
llmvault/cli/__init__.py
llmvault/cli/main.py
llmvault/core/__init__.py
llmvault/core/config.py
llmvault/core/yaml_config.py
llmvault/providers/__init__.py
llmvault/providers/anthropic_provider.py
llmvault/providers/base.py
llmvault/providers/ollama_provider.py
llmvault/providers/openai_compat.py
llmvault/providers/registry.py
llmvault/reporters/__init__.py
llmvault/reporters/cli_reporter.py
llmvault/reporters/html_reporter.py
llmvault/reporters/json_reporter.py
llmvault/reporters/sarif_reporter.py
llmvault/reporters/templates/report.html
llmvault/runner/__init__.py
llmvault/runner/engine.py
llmvault/runner/evaluator.py
llmvault/runner/evaluator_loader.py
llmvault/runner/models.py
llmvault/runner/rate_limiter.py
llmvault-0.1.0.dist-info/METADATA
llmvault-0.1.0.dist-info/WHEEL
llmvault-0.1.0.dist-info/entry_points.txt
llmvault-0.1.0.dist-info/licenses/LICENSE
llmvault-0.1.0.dist-info/RECORD
