Metadata-Version: 2.4
Name: llmvault
Version: 0.1.0
Summary: Security testing toolkit for LLM prompt injection vulnerabilities
Project-URL: Homepage, https://github.com/sharkfabri/LLMVault
Project-URL: Issues, https://github.com/sharkfabri/LLMVault/issues
Author: Fabrizio
License-Expression: MIT
License-File: LICENSE
Keywords: llm,prompt-injection,security,testing
Classifier: Development Status :: 3 - Alpha
Classifier: Intended Audience :: Developers
Classifier: License :: OSI Approved :: MIT License
Classifier: Programming Language :: Python :: 3
Classifier: Programming Language :: Python :: 3.10
Classifier: Programming Language :: Python :: 3.11
Classifier: Programming Language :: Python :: 3.12
Classifier: Programming Language :: Python :: 3.13
Classifier: Topic :: Security
Requires-Python: >=3.10
Requires-Dist: aiohttp>=3.9
Requires-Dist: jinja2>=3.0
Requires-Dist: pydantic>=2.0
Requires-Dist: pyyaml>=6.0
Requires-Dist: rich>=13.0
Requires-Dist: typer>=0.9
Provides-Extra: all
Requires-Dist: anthropic>=0.20; extra == 'all'
Requires-Dist: ollama>=0.1; extra == 'all'
Requires-Dist: openai>=1.0; extra == 'all'
Provides-Extra: anthropic
Requires-Dist: anthropic>=0.20; extra == 'anthropic'
Provides-Extra: deepseek
Requires-Dist: openai>=1.0; extra == 'deepseek'
Provides-Extra: dev
Requires-Dist: mypy>=1.0; extra == 'dev'
Requires-Dist: pre-commit>=3.0; extra == 'dev'
Requires-Dist: pytest-asyncio>=0.21; extra == 'dev'
Requires-Dist: pytest-cov>=4.0; extra == 'dev'
Requires-Dist: pytest>=7.0; extra == 'dev'
Requires-Dist: ruff>=0.4; extra == 'dev'
Requires-Dist: types-pyyaml>=6.0; extra == 'dev'
Provides-Extra: ollama
Requires-Dist: ollama>=0.1; extra == 'ollama'
Provides-Extra: openai
Requires-Dist: openai>=1.0; extra == 'openai'
